rag_document_viewer/__init__.py
rag_document_viewer/preprocess-custom-scripts_normal.js
rag_document_viewer/preprocess-custom-scripts_sheet.js
rag_document_viewer/preprocess-custom-styles_normal.css
rag_document_viewer/preprocess-custom-styles_sheet.css
rag_document_viewer/rag_document_viewer.py
rag_document_viewer-1.1.2.dist-info/LICENSE
rag_document_viewer-1.1.2.dist-info/METADATA
rag_document_viewer-1.1.2.dist-info/WHEEL
rag_document_viewer-1.1.2.dist-info/top_level.txt
rag_document_viewer-1.1.2.dist-info/RECORD
