Metadata-Version: 2.1
Name: rag-document-viewer
Version: 1.1.2
Summary: RAG Document Viewer
Home-page: https://github.com/preprocess-co/rag-document-viewer
Author: Preprocess
Author-email: <support@preprocess.co>
Keywords: python,python3,preprocess,chunks,paragraphs,chunk,paragraph,llama,llamaondex,langchain,chunking,llm,rag,document,view,viewer,preview,previewer,file
Classifier: Development Status :: 4 - Beta
Classifier: Intended Audience :: Developers
Classifier: Programming Language :: Python :: 3.9
Classifier: Programming Language :: Python :: 3.10
Classifier: Programming Language :: Python :: 3.11
Classifier: Programming Language :: Python :: 3.12
Classifier: Operating System :: Unix
Classifier: Operating System :: MacOS :: MacOS X
Classifier: Operating System :: Microsoft :: Windows
Classifier: License :: OSI Approved :: MIT License
Classifier: Topic :: Software Development :: Libraries :: Python Modules
Requires-Python: >=3.9
License-File: LICENSE
Requires-Dist: beautifulsoup4
